{
    "aovpn" : { 
        "config" : "/etc/aovpn",
	"version" : "2.0 Spiderman",
	"release" : "Ongoing 2019",
        "service" : {
		"centos" : "etc/systemd/system"
		},
	"advance" : {
		"enable" : "false",
		"ftp" : "false",
		"encrypt" : "false"
		},
	"web" : "false"
    	},
    "vpn" : {
    	"proto" : "tcp",
	"port" : "1194",
	"tunnel" : "192.165.10.0",
	"interface" : "eth0",
	"plus" : {
		"enable" : "false",
		"client2client" : "false"
		}
  	},
    "os" : {
	"ip" : "192.168.101.32"
	}
}
